biomodels_qc/__init__.py
biomodels_qc/__main__.py
biomodels_qc/_version.py
biomodels_qc/convert.py
biomodels_qc/utils.py
biomodels_qc/validation.py
biomodels_qc/warnings.py
biomodels_qc-0.0.3.dist-info/entry_points.txt
biomodels_qc-0.0.3.dist-info/LICENSE
biomodels_qc-0.0.3.dist-info/METADATA
biomodels_qc-0.0.3.dist-info/WHEEL
biomodels_qc-0.0.3.dist-info/RECORD
