Metadata-Version: 2.3
Name: biomodels_qc
Version: 0.0.3
Summary: Utility functions to assist biomodels curation.
License: MIT
Keywords: systems,biology,modeling,simulation
Author: Center for Reproducible Biomedical Modeling
Author-email: info@biosimulators.org
Requires-Python: >=3.9,<4.0
Classifier: Development Status :: 3 - Alpha
Classifier: Intended Audience :: Science/Research
Classifier: License :: OSI Approved :: MIT License
Classifier: Programming Language :: Python :: 3
Classifier: Programming Language :: Python :: 3.9
Classifier: Programming Language :: Python :: 3.10
Classifier: Programming Language :: Python :: 3.11
Classifier: Programming Language :: Python :: 3.12
Classifier: Programming Language :: Python :: 3.13
Classifier: Topic :: Scientific/Engineering :: Bio-Informatics
Requires-Dist: biosimulators_utils (>=0.1.171,<0.2.0)
Requires-Dist: cement (>=3.0,<4.0)
Requires-Dist: kisao (>=2.0,<3.0)
Requires-Dist: lxml (>=5.0,<6.0)
Requires-Dist: nbformat (>=5.0,<6.0)
Requires-Dist: owlready2 (>=0.4,<0.5)
Requires-Dist: pypdf2 (>=3.0,<4.0)
Requires-Dist: python_copasi (>=4.0,<5.0)
Requires-Dist: python_dateutil (>=2.0,<3.0)
Requires-Dist: python_libsbml (>=5.0,<6.0)
Requires-Dist: scipy (>=1.0,<2.0)
Requires-Dist: termcolor (>=3.0,<4.0)
Requires-Dist: xmldiff (>=2.0,<3.0)
Project-URL: Homepage, https://biosimulations.github.io/biomodels-qc/
Project-URL: Repository, https://github.com/biosimulations/biomodels-qc/
